app_sales/__init__.py
app_sales/descuentos.py
app_sales/exceptions.py
app_sales/gestor_ventas.py
app_sales/impuestos.py
app_sales/precios.py
app_sales-0.1.1.dist-info/licenses/LICENCE
tests/__init__.py
tests/test_app_sales.py
app_sales-0.1.1.dist-info/METADATA
app_sales-0.1.1.dist-info/WHEEL
app_sales-0.1.1.dist-info/top_level.txt
app_sales-0.1.1.dist-info/RECORD
